{
    "took": 1,
    "timed_out": false,
    "_shards": {
        "total": 1,
        "successful": 1,
        "skipped": 0,
        "failed": 0
    },
    "hits": {
        "total": {
            "value": 48,
            "relation": "eq"
        },
        "max_score": 1.0,
        "hits": [
            {
                "_index": "dummy_index",
                "_id": "a004a191-31d2-421e-a514-7b1021c1fa78",
                "_score": 1.0,
                "_source": {
                    "fragmentTitleSuggest": "Change your password",
                    "fragmentTitle": "Change your password",
                    "shortDescriptionEmbedding": {
                        "screen": 0.10833981,
                        "your": 0.25542533,
                        "employee": 0.33904883,
                        "secure": 0.084712125,
                        "locker": 0.22147122,
                        "password": 1.8081923,
                        "bank": 1.4679917,
                        "ref": 0.18119782,
                        "download": 0.1534428,
                        "tab": 0.60902566,
                        "logo": 0.5529907,
                        "lock": 0.28576687,
                        "payment": 0.14815018,
                        "enter": 0.41391936,
                        "atm": 0.30341834,
                        "credit": 0.16996533,
                        "app": 1.2366228,
                        "unlock": 0.24133596,
                        "package": 0.07017952,
                        "banks": 0.4978296,
                        "need": 0.02335597,
                        "profile": 0.3446178,
                        "pay": 0.0013625871,
                        "check": 0.12738007,
                        "my": 0.25660905,
                        "badge": 0.07005527,
                        "transfer": 0.017841212,
                        "phone": 0.42572615,
                        "rama": 0.0037687244,
                        "deposit": 0.6430814,
                        "reset": 0.4834409,
                        "registration": 0.18375723,
                        "page": 0.343345,
                        "<": 0.49610278,
                        "card": 0.4657287,
                        "##ran": 0.19127671,
                        "loan": 0.30309987,
                        "log": 0.8957692,
                        "document": 0.17677124,
                        "save": 0.016617693,
                        "membership": 0.26183534,
                        "malaysia": 0.21489534,
                        "sun": 2.0494983,
                        "remove": 0.32574221,
                        "banking": 0.5169728,
                        "sid": 0.06429558,
                        "button": 0.52687705,
                        "into": 0.52355915,
                        "apple": 0.16918042,
                        "security": 0.24107811,
                        "sim": 0.33634704,
                        "identity": 0.18256456,
                        "company": 0.1893827,
                        "key": 0.47065103,
                        "##corp": 1.4197786,
                        "mask": 0.16309729,
                        "website": 0.2860379,
                        "wallet": 0.1888199,
                        "comply": 0.0431528,
                        "change": 0.8808061,
                        "mobile": 0.5741647,
                        "withdrawal": 0.18417348,
                        "p": 0.2777619,
                        "singapore": 0.11586622,
                        "application": 0.6684383,
                        "online": 0.8687141,
                        "user": 0.53441703,
                        "account": 0.7265595,
                        "finance": 0.0781604
                    },
                    "shortDescription": "<p>Change the password you use to log into the Suncorp Bank App</p>",
                    "model_id": ".elser_model_2",
                    "uuid": "a004a191-31d2-421e-a514-7b1021c1fa78",
                    "resultType": "selfServiceTask",
                    "url": "suncorp-marketplace://change-password",
                    "fragmentChannel": "app",
                    "tags": [
                        "support-hub:login",
                        "support-hub:suncorp-bank-app"
                    ]
                }
            },
            {
                "_index": "dummy_index",
                "_id": "d2fd3aba-d251-4e33-862e-4e42971e7cc0",
                "_score": 1.0,
                "_source": {
                    "fragmentTitleSuggest": "Close an account",
                    "fragmentTitle": "Close an account",
                    "shortDescriptionEmbedding": {
                        "cancel": 0.3592172,
                        "shut": 0.056496464,
                        "del": 0.42539752,
                        "section": 0.2909276,
                        "accounting": 0.4363345,
                        "your": 0.27478793,
                        "retirement": 0.63252944,
                        "employee": 0.1024967,
                        "loss": 0.0054575023,
                        "bank": 0.6851611,
                        "ref": 0.32643613,
                        "closing": 0.27919698,
                        "tab": 0.4116045,
                        "balance": 0.36280182,
                        "leave": 0.269922,
                        "tip": 0.16967733,
                        "payment": 0.136664,
                        "ren": 0.115242936,
                        "savings": 1.2397059,
                        "surrender": 0.30931947,
                        "termination": 0.21856163,
                        "item": 0.006700429,
                        "agreement": 0.03366583,
                        "last": 0.11658811,
                        "contract": 0.27921754,
                        "personal": 1.5055856,
                        "transactions": 0.5934747,
                        "my": 0.17993207,
                        "remaining": 0.32341912,
                        "important": 0.08959232,
                        "saving": 0.68611616,
                        "exit": 0.45158112,
                        "transfer": 0.12542607,
                        "stop": 0.48136085,
                        "fraud": 0.2730567,
                        "failure": 0.16222061,
                        "final": 0.0643983,
                        "deposit": 0.58967525,
                        "page": 0.5358977,
                        "<": 0.9891093,
                        "debt": 0.37048766,
                        ">": 0.23909019,
                        "status": 0.5335487,
                        "option": 0.052726712,
                        "denial": 0.115571246,
                        "trust": 0.10418249,
                        "sub": 1.3396579,
                        "deal": 0.09510503,
                        "penalty": 0.637827,
                        "advice": 0.22137043,
                        "document": 0.5590389,
                        "membership": 0.30286548,
                        "bankruptcy": 0.6737131,
                        "remove": 0.4919965,
                        "button": 0.4474284,
                        "default": 0.16616407,
                        "audit": 0.007417992,
                        "ira": 0.1768976,
                        "end": 0.7791627,
                        "close": 1.5487348,
                        "liquidation": 0.10319099,
                        "comply": 0.3527447,
                        "sell": 0.40210786,
                        "change": 0.13137798,
                        "withdrawal": 1.0603676,
                        "broker": 0.44532257,
                        "consolidation": 0.3673885,
                        "flu": 0.017905617,
                        "p": 0.744556,
                        "sale": 0.3495211,
                        "management": 0.26190114,
                        "service": 0.35832527,
                        "isa": 0.083552994,
                        "removal": 0.33971465,
                        "closed": 0.9499277,
                        "step": 0.4029393,
                        "trustee": 0.31593156,
                        "quit": 0.03868799,
                        "accounts": 0.6503688,
                        "under": 6.580571E-4,
                        "bankrupt": 0.22464313,
                        "maintenance": 0.07969221,
                        "account": 1.501024,
                        "transaction": 1.3849001,
                        "collapse": 0.35357648,
                        "withdraw": 0.7053114
                    },
                    "shortDescription": "<p>Close a personal transaction account, savings account or sub-account.</p>",
                    "model_id": ".elser_model_2",
                    "uuid": "d2fd3aba-d251-4e33-862e-4e42971e7cc0",
                    "resultType": "selfServiceTask",
                    "url": "suncorp-marketplace://website-single-sign-on?landingPage=HelpTopics&title=Accounts&destinationUrl=https%3A%2F%2Fwww.suncorpbank.com.au%2Fsunapps%2Fforms%2Ftransfer%3Fredirect%3Dhttps%3A%2F%2Fwww.suncorpbank.com.au%2Fsunapps%2Fforms%2Fpkceauth%3Ftask%3Dca",
                    "fragmentChannel": "app",
                    "tags": [
                        "support-hub:accounts",
                        "support-hub:close",
                        "support-hub:suncorp-bank-app"
                    ]
                }
            },
            {
                "_index": "dummy_index",
                "_id": "1fc65bf5-3c04-41a1-ab8b-e5917f6b1e18",
                "_score": 1.0,
                "_source": {
                    "fragmentTitleSuggest": "Manage your eStatement preferences",
                    "fragmentTitle": "Manage your eStatement preferences",
                    "shortDescriptionEmbedding": {
                        "your": 0.578534,
                        "changing": 0.36375234,
                        "via": 0.027849497,
                        "bank": 1.6952133,
                        "balance": 0.51421076,
                        "draft": 0.24348287,
                        "payment": 0.6308181,
                        "shopping": 0.07324169,
                        "item": 0.044106275,
                        "method": 0.5013393,
                        "banks": 0.37744212,
                        "contract": 0.11977402,
                        "bill": 0.47716203,
                        "received": 0.2748153,
                        "letter": 0.18397862,
                        "deposit": 0.88277113,
                        "processing": 0.61874896,
                        "difference": 0.22175366,
                        "<": 0.9409304,
                        "card": 0.34876862,
                        ">": 0.06644838,
                        "signature": 0.10129434,
                        "document": 0.73203975,
                        "paperwork": 0.018941477,
                        "distribution": 0.071668334,
                        "receiving": 0.7113471,
                        "how": 0.28630367,
                        "routing": 0.27666798,
                        "file": 0.45001745,
                        "web": 0.16552056,
                        "audit": 0.30401805,
                        "identity": 0.20237745,
                        "get": 0.4713669,
                        "electronic": 0.15981899,
                        "currency": 0.067710504,
                        "email": 0.33189338,
                        "receive": 0.67670184,
                        "website": 0.4618374,
                        "change": 1.1474258,
                        "withdrawal": 0.53028345,
                        "irs": 0.37738785,
                        "declaration": 0.09370034,
                        "reconciliation": 0.25538903,
                        "p": 0.61102253,
                        "report": 0.6264585,
                        "transaction": 0.6696315,
                        "acc": 0.17557849,
                        "de": 0.08764915,
                        "mail": 1.2473595,
                        "declare": 0.07406275,
                        "accounting": 0.4957599,
                        "ref": 0.7547057,
                        "tab": 0.45996368,
                        "tip": 0.26312047,
                        "atm": 0.0051117204,
                        "bureau": 7.995746E-4,
                        "different": 0.5643123,
                        "credit": 0.14757128,
                        "qualify": 0.078462765,
                        "alter": 0.086842455,
                        "package": 0.3887593,
                        "amend": 0.16376746,
                        "format": 0.14034629,
                        "pay": 0.38088557,
                        "archive": 0.036571298,
                        "check": 0.47614977,
                        "my": 0.1249397,
                        "modification": 0.38502932,
                        "important": 0.20245077,
                        "qualification": 0.14023885,
                        "transfer": 0.40152115,
                        "fraud": 0.4357947,
                        "treasury": 0.35003608,
                        "provision": 0.29231417,
                        "receipt": 0.3524137,
                        "postal": 0.5109838,
                        "page": 0.43118587,
                        "fa": 0.026840933,
                        "send": 0.29739845,
                        "option": 0.50666463,
                        "changed": 0.046149954,
                        "loan": 0.2478556,
                        "submit": 0.16810687,
                        "penalty": 0.3020327,
                        "changes": 0.38654307,
                        "statements": 1.4191589,
                        "box": 0.080218464,
                        "levy": 0.037463088,
                        "banking": 0.22972736,
                        "button": 0.2826231,
                        "paper": 0.27127266,
                        "provider": 0.18271938,
                        "statement": 1.3490423,
                        "notice": 0.019154226,
                        "delivery": 0.5294318,
                        "process": 0.25049102,
                        "comply": 0.73743033,
                        "custom": 0.31457326,
                        "alternative": 0.25349787,
                        "automatic": 0.111143604,
                        "message": 0.1353157,
                        "way": 0.01180767,
                        "print": 0.18043293,
                        "pdf": 0.17311183,
                        "form": 0.4214311,
                        "application": 0.19344983,
                        "regulation": 0.02192905,
                        "service": 0.1416387,
                        "online": 1.2207564,
                        "handling": 0.29039854,
                        "step": 0.13425809,
                        "account": 0.54833794,
                        "withdraw": 0.06732675
                    },
                    "shortDescription": "<p>Change how you receive your bank statements, either online or by mail.</p>",
                    "model_id": ".elser_model_2",
                    "uuid": "1fc65bf5-3c04-41a1-ab8b-e5917f6b1e18",
                    "resultType": "selfServiceTask",
                    "url": "suncorp-marketplace://document-preferences",
                    "fragmentChannel": "app",
                    "tags": [
                        "support-hub:statements",
                        "support-hub:suncorp-bank-app"
                    ]
                }
            }
        ]
    }
}